{
	"name": "Mario 1-2",
	"start": "False",
	"dimensions": {
		"width": 200,
		"height": 20
	},
	"file": ["sprites/Mario_Tiles_01.png"],
	"bgcolor": {
		"red": 240,
		"green": 123,
		"blue": 255
	},
	"background_fill": {
		"red": 0,
		"green": 0,
		"blue": 0
	},
	"player_start":{ 
		"x": 2,"y": 15
	},
	"menu_tile": "sprites/Mario_1_1.png",
	"sprites": [{
		"name": "brick",
		"x": 0,
		"y": 51,
		"w": 50,
		"h": 50
	},
	{
		"name": "b_brick",
		"x": 50,
		"y": 51,
		"w": 50,
		"h": 50
	},
	{
		"name": "pipe_top_left",
		"x": 100,
		"y": 0,
		"w": 50,
		"h": 50
	},
	{
		"name": "pipe_top_right",
		"x": 150,
		"y": 0,
		"w": 50,
		"h": 50
	},
	{
		"name": "?_block",
		"x": 200,
		"y": 50,
		"w": 50,
		"h": 50
	},
	{
		"name": "h_block",
		"x": 250,
		"y": 51,
		"w": 50,
		"h": 50
	},
	{
		"name": "ladder",
		"x": 300,
		"y": 0,
		"w": 50,
		"h": 50
	},
	{
		"name": "pipe_bottom_left",
		"x": 100,
		"y": 50,
		"w": 50,
		"h": 50
	},
	{
		"name": "pipe_bottom_right",
		"x": 150,
		"y": 50,
		"w": 50,
		"h": 50
	},
	{
		"name": "door",
		"x": 350,
		"y": 0,
		"w": 50,
		"h": 50
	}],
	"scenery":[],
	"ladders":[
	{
		"tile": "ladder",
		"set":[ {"x": 52,"y": 8,"w": 1,"h": 11},
				{"x": 183,"y": 0,"w": 1,"h": 19}]
	}],
	"doors":[{
		"level": "Mario 1-1",
		"tile": "door",
		"x": 0,
		"y": 15,
		"player_x": 10650,
		"player_y": 880,
		"player_f": "L"
	},
	{
		"level": "Mario 1-3",
		"tile": "door",
		"x": 173,
		"y": 12,
		"player_x": 50,
		"player_y": 730,
		"player_f": "R"
	}],
	"spawners":[{
		"type": "Platform",
		"sprite": "Red_Platform",
		"x": 158,
		"y": 6,
		"d": "D",
		"speed": {"x":0,"y":2},
		"limit": -1,
		"freq": 210
	},{
		"type": "Platform",
		"sprite": "Red_Platform",
		"x": 143,
		"y": 6,
		"d": "D",
		"speed": {"x":0,"y":2},
		"limit": -1,
		"freq": 210
	}],
	"monsters":[{
		"file": "enemies/goomba.json",
		"location":[
			{"x": 25,"y": 18}, 
			{"x": 43,"y": 18},
			{"x": 54,"y": 18},
			{"x": 56,"y": 18},
			{"x": 83,"y": 10},
			{"x": 85,"y": 10},
			{"x": 99,"y": 18},
			{"x": 101,"y": 18},
			{"x": 117,"y": 18},
			{"x": 119,"y": 18},
			{"x": 122,"y": 18},
			{"x": 124,"y": 18},
			{"x": 177,"y": 18},
			{"x": 175,"y": 18}
		]
	}],
	"platforms": [{
		"tile": "brick",
		"set":[
			{"x": 0,"y": 19,"w": 80,"h": 2},
			{"x": -1,"y": 0,"w": 1,"h": 20},
			{"x": 201,"y": 0,"w": 1,"h": 20},
			{"x": 84,"y": 19,"w": 20,"h": 2},
			{"x": 106,"y": 19,"w": 15,"h": 2},
			{"x": 123,"y": 19,"w": 2,"h": 2},
			{"x": 127,"y": 19,"w": 12,"h": 2},
			{"x": 147,"y": 19,"w": 8,"h": 2},
			{"x": 163,"y": 19,"w": 40,"h": 2}]
	},
	{
		"tile": "b_brick",
		"set":[
			{"x": 0,"y": 0,"w": 139,"h": 8},
			{"x": 0,"y": 0,"w": 2,"h": 15},
			{"x": 30,"y": 14,"w": 1,"h": 1},
			{"x": 40,"y": 13,"w": 1,"h": 3},
			{"x": 41,"y": 15,"w": 1,"h": 1},
			{"x": 42,"y": 13,"w": 1,"h": 3},
			{"x": 45,"y": 13,"w": 1,"h": 3},
			{"x": 47,"y": 13,"w": 1,"h": 3},
			{"x": 43,"y": 13,"w": 2,"h": 1},
			{"x": 46,"y": 15,"w": 1,"h": 1},
			{"x": 53,"y": 10,"w": 2,"h": 6},
			{"x": 55,"y": 15,"w": 2,"h": 4},
			{"x": 59,"y": 8,"w": 6,"h": 2},
			{"x": 63,"y": 10,"w": 2,"h": 5},
			{"x": 59,"y": 15,"w": 6,"h": 1},
			{"x": 65,"y": 8,"w": 6,"h": 2},
			{"x": 67,"y": 10,"w": 1,"h": 6},
			{"x": 68,"y": 15,"w": 1,"h": 1},
			{"x": 69,"y": 14,"w": 1,"h": 2},
			{"x": 72,"y": 10,"w": 2,"h": 6},
			{"x": 76,"y": 8,"w": 4,"h": 2},
			{"x": 76,"y": 15,"w": 4,"h": 1},
			{"x": 85,"y": 13,"w": 6,"h": 2},
			{"x": 123,"y": 16,"w": 2,"h": 3},
			{"x": 147,"y": 15,"w": 6,"h": 1},
			{"x": 163,"y": 16,"w": 20,"h": 3},
			{"x": 164,"y": 0,"w": 19,"h": 8},
			{"x": 173,"y": 8,"w": 10,"h": 5}]
	},
	{
		"tile": "?_block",
		"set":[{"x": 11,"y": 15,"w": 5,"h": 1}]
	},
	{
		"tile": "pipe_bottom_left",
		"set":[
			{"x": 104,"y": 17,"w": 1,"h": 4},
			{"x": 110,"y": 15,"w": 1,"h": 4},
			{"x": 116,"y": 18,"w": 1,"h": 3}]
	},
	{
		"tile": "pipe_bottom_right",
		"set":[
			{"x": 105,"y": 17,"w": 1,"h": 4},			
			{"x": 111,"y": 15,"w": 1,"h": 4},
			{"x": 117,"y": 18,"w": 1,"h": 3}]
	},
	{
		"tile": "pipe_top_left",
		"set":[
			{"x": 104,"y": 16,"w": 1,"h": 1},
			{"x": 110,"y": 14,"w": 1,"h": 1},
			{"x": 116,"y": 17,"w": 1,"h": 1}]
	},
	{
		"tile": "pipe_top_right",
		"set":[
			{"x": 105,"y": 16,"w": 1,"h": 1},
			{"x": 111,"y": 14,"w": 1,"h": 1},
			{"x": 117,"y": 17,"w": 1,"h": 1}]
	},
	{
		"tile": "h_block",
		"set":[
			{"x": 18,"y": 18,"w": 1,"h": 1},
			{"x": 20,"y": 17,"w": 1,"h": 2},
			{"x": 22,"y": 16,"w": 1,"h": 3},
			{"x": 24,"y": 15,"w": 1,"h": 4},
			{"x": 26,"y": 15,"w": 1,"h": 4},
			{"x": 28,"y": 16,"w": 1,"h": 3},
			{"x": 32,"y": 16,"w": 1,"h": 3},
			{"x": 34,"y": 17,"w": 1,"h": 2},
			{"x": 134,"y": 18,"w": 5,"h": 1},
			{"x": 135,"y": 17,"w": 4,"h": 1},
			{"x": 136,"y": 16,"w": 3,"h": 1},
			{"x": 137,"y": 15,"w": 2,"h": 1},
			{"x": 174,"y": 13,"w": 9,"h": 3}]
	}]
}